{
   "housing":[
      {
         "firstName":"Hannah",
         "lastName":"Bedell",
         "priceRange":"2",
         "pets":"0",
         "smoking":"0",
         "pool":"1",
         "gym":"1",
         "parking":"1",
         "laundry":"1",
         "numRoomates":"1",
         "distanceToWork":"3",
         "roommateGender":"1",
         "typeOfResidence":"2"
      },
      {
         "firstName":"Russell",
         "lastName":"Mendleson",
         "priceRange":"1",
         "pets":"0",
         "smoking":"1",
         "pool":"1",
         "gym":"0",
         "parking":"1",
         "laundry":"1",
         "numRoomates":"3",
         "distanceToWork":"3",
         "roommateGender":"0",
         "typeOfResidence":"1"
      },
      {
         "firstName":"Mussttafa",
         "lastName":"Shelo",
         "priceRange":"3",
         "pets":"1",
         "smoking":"1",
         "pool":"0",
         "gym":"0",
         "parking":"1",
         "laundry":"0",
         "numRoomates":"2",
         "distanceToWork":"1",
         "roommateGender":"1",
         "typeOfResidence":"3"
      },
      {
         "firstName":"Laert",
         "lastName":"Skreli",
         "priceRange":"1",
         "pets":"1",
         "smoking":"1",
         "pool":"0",
         "gym":"0",
         "parking":"0",
         "laundry":"0",
         "numRoomates":"3",
         "distanceToWork":"3",
         "roommateGender":"1",
         "typeOfResidence":"1"
      },
      {
         "firstName":"Lily",
         "lastName":"Xu",
         "priceRange":"1",
         "pets":"0",
         "smoking":"1",
         "pool":"1",
         "gym":"0",
         "parking":"1",
         "laundry":"1",
         "numRoomates":"2",
         "distanceToWork":"2",
         "roommateGender":"0",
         "typeOfResidence":"3"
      },
      {
         "firstName":"Ravone",
         "lastName":"Cornish",
         "priceRange":"1",
         "pets":"1",
         "smoking":"0",
         "pool":"1",
         "gym":"1",
         "parking":"0",
         "laundry":"0",
         "numRoomates":"2",
         "distanceToWork":"2",
         "roommateGender":"0",
         "typeOfResidence":"1"
      },
      {
         "firstName":"Wyatt",
         "lastName":"Craig",
         "priceRange":"3",
         "pets":"0",
         "smoking":"1",
         "pool":"1",
         "gym":"0",
         "parking":"1",
         "laundry":"0",
         "numRoomates":"1",
         "distanceToWork":"1",
         "roommateGender":"1",
         "typeOfResidence":"1"
      },
      {
         "firstName":"Patrick",
         "lastName":"Johnson",
         "priceRange":"3",
         "pets":"1",
         "smoking":"1",
         "pool":"1",
         "gym":"0",
         "parking":"1",
         "laundry":"0",
         "numRoomates":"1",
         "distanceToWork":"2",
         "roommateGender":"0",
         "typeOfResidence":"3"
      },
      {
         "firstName":"Joe",
         "lastName":"Nutter",
         "priceRange":"2",
         "pets":"0",
         "smoking":"1",
         "pool":"1",
         "gym":"0",
         "parking":"0",
         "laundry":"1",
         "numRoomates":"2",
         "distanceToWork":"1",
         "roommateGender":"1",
         "typeOfResidence":"2"
      },
      {
         "firstName":"Colin",
         "lastName":"Quinlan",
         "priceRange":"1",
         "pets":"0",
         "smoking":"0",
         "pool":"0",
         "gym":"1",
         "parking":"0",
         "laundry":"0",
         "numRoomates":"3",
         "distanceToWork":"1",
         "roommateGender":"1",
         "typeOfResidence":"1"
      },
      {
         "firstName":"Ryan",
         "lastName":"Parker",
         "priceRange":"2",
         "pets":"1",
         "smoking":"1",
         "pool":"0",
         "gym":"1",
         "parking":"0",
         "laundry":"1",
         "numRoomates":"1",
         "distanceToWork":"3",
         "roommateGender":"0",
         "typeOfResidence":"2"
      },
      {
         "firstName":"Dan",
         "lastName":"Bertolino",
         "priceRange":"2",
         "pets":"1",
         "smoking":"0",
         "pool":"0",
         "gym":"0",
         "parking":"0",
         "laundry":"0",
         "numRoomates":"2",
         "distanceToWork":"3",
         "roommateGender":"0",
         "typeOfResidence":"1"
      },
      {
         "firstName":"Ramon",
         "lastName":"Cadeaux",
         "priceRange":"1",
         "pets":"1",
         "smoking":"0",
         "pool":"0",
         "gym":"1",
         "parking":"1",
         "laundry":"1",
         "numRoomates":"1",
         "distanceToWork":"2",
         "roommateGender":"0",
         "typeOfResidence":"1"
      },
      {
         "firstName":"Brandon",
         "lastName":"Cohen",
         "priceRange":"1",
         "pets":"0",
         "smoking":"1",
         "pool":"1",
         "gym":"0",
         "parking":"1",
         "laundry":"0",
         "numRoomates":"1",
         "distanceToWork":"3",
         "roommateGender":"1",
         "typeOfResidence":"3"
      },
      {
         "firstName":"Stephen",
         "lastName":"Ecsedy",
         "priceRange":"3",
         "pets":"1",
         "smoking":"1",
         "pool":"0",
         "gym":"0",
         "parking":"0",
         "laundry":"0",
         "numRoomates":"2",
         "distanceToWork":"2",
         "roommateGender":"1",
         "typeOfResidence":"2"
      },
      {
         "firstName":"Dan",
         "lastName":"Garofalo",
         "priceRange":"2",
         "pets":"0",
         "smoking":"0",
         "pool":"0",
         "gym":"0",
         "parking":"0",
         "laundry":"0",
         "numRoomates":"1",
         "distanceToWork":"2",
         "roommateGender":"1",
         "typeOfResidence":"3"
      },
      {
         "firstName":"Ben",
         "lastName":"Nader",
         "priceRange":"2",
         "pets":"0",
         "smoking":"1",
         "pool":"1",
         "gym":"1",
         "parking":"0",
         "laundry":"1",
         "numRoomates":"2",
         "distanceToWork":"3",
         "roommateGender":"1",
         "typeOfResidence":"1"
      },
      {
         "firstName":"Patrick",
         "lastName":"O'Brien",
         "priceRange":"2",
         "pets":"1",
         "smoking":"0",
         "pool":"0",
         "gym":"1",
         "parking":"1",
         "laundry":"1",
         "numRoomates":"2",
         "distanceToWork":"2",
         "roommateGender":"0",
         "typeOfResidence":"2"
      },
      {
         "firstName":"Ravi",
         "lastName":"Patel",
         "priceRange":"1",
         "pets":"0",
         "smoking":"0",
         "pool":"1",
         "gym":"0",
         "parking":"0",
         "laundry":"0",
         "numRoomates":"3",
         "distanceToWork":"1",
         "roommateGender":"0",
         "typeOfResidence":"1"
      },
      {
         "firstName":"Stephen ",
         "lastName":"Ptucha",
         "priceRange":"3",
         "pets":"1",
         "smoking":"1",
         "pool":"0",
         "gym":"1",
         "parking":"0",
         "laundry":"1",
         "numRoomates":"2",
         "distanceToWork":"3",
         "roommateGender":"0",
         "typeOfResidence":"1"
      },
      {
         "firstName":"Katie",
         "lastName":"Senk",
         "priceRange":"2",
         "pets":"1",
         "smoking":"1",
         "pool":"1",
         "gym":"1",
         "parking":"1",
         "laundry":"1",
         "numRoomates":"1",
         "distanceToWork":"2",
         "roommateGender":"0",
         "typeOfResidence":"2"
      },
      {
         "firstName":"Joanne",
         "lastName":"Swanson",
         "priceRange":"3",
         "pets":"1",
         "smoking":"1",
         "pool":"0",
         "gym":"1",
         "parking":"1",
         "laundry":"0",
         "numRoomates":"3",
         "distanceToWork":"1",
         "roommateGender":"1",
         "typeOfResidence":"1"
      },
      {
         "firstName":"Marshall",
         "lastName":"Beach",
         "priceRange":"2",
         "pets":"1",
         "smoking":"1",
         "pool":"0",
         "gym":"1",
         "parking":"0",
         "laundry":"0",
         "numRoomates":"1",
         "distanceToWork":"3",
         "roommateGender":"0",
         "typeOfResidence":"3"
      },
      {
         "firstName":"Kiara",
         "lastName":"Burroughs",
         "priceRange":"3",
         "pets":"0",
         "smoking":"0",
         "pool":"0",
         "gym":"0",
         "parking":"1",
         "laundry":"1",
         "numRoomates":"3",
         "distanceToWork":"3",
         "roommateGender":"1",
         "typeOfResidence":"3"
      },
      {
         "firstName":"Brandon",
         "lastName":"Kelly",
         "priceRange":"1",
         "pets":"0",
         "smoking":"1",
         "pool":"0",
         "gym":"1",
         "parking":"1",
         "laundry":"0",
         "numRoomates":"3",
         "distanceToWork":"2",
         "roommateGender":"1",
         "typeOfResidence":"1"
      },
      {
         "firstName":"Jeff",
         "lastName":"Kim",
         "priceRange":"2",
         "pets":"1",
         "smoking":"0",
         "pool":"0",
         "gym":"0",
         "parking":"0",
         "laundry":"1",
         "numRoomates":"2",
         "distanceToWork":"2",
         "roommateGender":"0",
         "typeOfResidence":"3"
      },
      {
         "firstName":"Kyle",
         "lastName":"Krueger",
         "priceRange":"1",
         "pets":"1",
         "smoking":"0",
         "pool":"0",
         "gym":"0",
         "parking":"1",
         "laundry":"0",
         "numRoomates":"1",
         "distanceToWork":"2",
         "roommateGender":"0",
         "typeOfResidence":"1"
      },
      {
         "firstName":"Kurt",
         "lastName":"Ostlund",
         "priceRange":"1",
         "pets":"1",
         "smoking":"0",
         "pool":"1",
         "gym":"1",
         "parking":"0",
         "laundry":"1",
         "numRoomates":"2",
         "distanceToWork":"1",
         "roommateGender":"0",
         "typeOfResidence":"3"
      },
      {
         "firstName":"Haykaz",
         "lastName":"Sargisov",
         "priceRange":"2",
         "pets":"0",
         "smoking":"1",
         "pool":"0",
         "gym":"0",
         "parking":"1",
         "laundry":"0",
         "numRoomates":"1",
         "distanceToWork":"1",
         "roommateGender":"1",
         "typeOfResidence":"3"
      },
      {
         "firstName":"Molly",
         "lastName":"Whitlock",
         "priceRange":"3",
         "pets":"0",
         "smoking":"0",
         "pool":"1",
         "gym":"1",
         "parking":"1",
         "laundry":"0",
         "numRoomates":"1",
         "distanceToWork":"1",
         "roommateGender":"1",
         "typeOfResidence":"2"
      },
      {
         "firstName":"Anthony",
         "lastName":"Donadio",
         "priceRange":"1",
         "pets":"1",
         "smoking":"1",
         "pool":"0",
         "gym":"0",
         "parking":"0",
         "laundry":"0",
         "numRoomates":"1",
         "distanceToWork":"3",
         "roommateGender":"0",
         "typeOfResidence":"3"
      },
      {
         "firstName":"Melvin",
         "lastName":"Owens III",
         "priceRange":"1",
         "pets":"0",
         "smoking":"0",
         "pool":"1",
         "gym":"1",
         "parking":"0",
         "laundry":"1",
         "numRoomates":"2",
         "distanceToWork":"1",
         "roommateGender":"0",
         "typeOfResidence":"1"
      },
      {
         "firstName":"Patrick",
         "lastName":"Thibodeaux",
         "priceRange":"2",
         "pets":"1",
         "smoking":"1",
         "pool":"0",
         "gym":"0",
         "parking":"1",
         "laundry":"1",
         "numRoomates":"3",
         "distanceToWork":"3",
         "roommateGender":"0",
         "typeOfResidence":"2"
      },
      {
         "firstName":"Levi",
         "lastName":"Hopkins",
         "priceRange":"1",
         "pets":"0",
         "smoking":"1",
         "pool":"0",
         "gym":"0",
         "parking":"0",
         "laundry":"1",
         "numRoomates":"1",
         "distanceToWork":"3",
         "roommateGender":"0",
         "typeOfResidence":"3"
      },
      {
         "firstName":"Frank",
         "lastName":"Zhao",
         "priceRange":"3",
         "pets":"1",
         "smoking":"0",
         "pool":"0",
         "gym":"0",
         "parking":"1",
         "laundry":"0",
         "numRoomates":"3",
         "distanceToWork":"3",
         "roommateGender":"1",
         "typeOfResidence":"2"
      },
      {
         "firstName":"John",
         "lastName":"Taylor",
         "priceRange":"2",
         "pets":"1",
         "smoking":"0",
         "pool":"0",
         "gym":"0",
         "parking":"1",
         "laundry":"0",
         "numRoomates":"2",
         "distanceToWork":"1",
         "roommateGender":"0",
         "typeOfResidence":"1"
      },
      {
         "firstName":"Maquet",
         "lastName":"Dean",
         "priceRange":"1",
         "pets":"1",
         "smoking":"0",
         "pool":"1",
         "gym":"1",
         "parking":"1",
         "laundry":"0",
         "numRoomates":"2",
         "distanceToWork":"1",
         "roommateGender":"1",
         "typeOfResidence":"2"
      },
      {
         "firstName":"Doug",
         "lastName":"Diedrick",
         "priceRange":"3",
         "pets":"1",
         "smoking":"1",
         "pool":"1",
         "gym":"1",
         "parking":"0",
         "laundry":"0",
         "numRoomates":"3",
         "distanceToWork":"3",
         "roommateGender":"1",
         "typeOfResidence":"2"
      },
      {
         "firstName":"Justin",
         "lastName":"Eberly",
         "priceRange":"1",
         "pets":"0",
         "smoking":"1",
         "pool":"1",
         "gym":"0",
         "parking":"0",
         "laundry":"1",
         "numRoomates":"2",
         "distanceToWork":"1",
         "roommateGender":"1",
         "typeOfResidence":"3"
      },
      {
         "firstName":"Sofia",
         "lastName":"Grossman Pena",
         "priceRange":"3",
         "pets":"0",
         "smoking":"0",
         "pool":"1",
         "gym":"0",
         "parking":"0",
         "laundry":"1",
         "numRoomates":"1",
         "distanceToWork":"3",
         "roommateGender":"0",
         "typeOfResidence":"3"
      },
      {
         "firstName":"Philip",
         "lastName":"Gyampo",
         "priceRange":"1",
         "pets":"1",
         "smoking":"1",
         "pool":"1",
         "gym":"1",
         "parking":"1",
         "laundry":"0",
         "numRoomates":"1",
         "distanceToWork":"1",
         "roommateGender":"1",
         "typeOfResidence":"1"
      },
      {
         "firstName":"Ryan",
         "lastName":"Hayes",
         "priceRange":"2",
         "pets":"0",
         "smoking":"1",
         "pool":"0",
         "gym":"1",
         "parking":"0",
         "laundry":"0",
         "numRoomates":"1",
         "distanceToWork":"3",
         "roommateGender":"0",
         "typeOfResidence":"3"
      },
      {
         "firstName":"Manuel",
         "lastName":"Roman",
         "priceRange":"3",
         "pets":"1",
         "smoking":"1",
         "pool":"1",
         "gym":"1",
         "parking":"0",
         "laundry":"0",
         "numRoomates":"1",
         "distanceToWork":"3",
         "roommateGender":"0",
         "typeOfResidence":"3"
      },
      {
         "firstName":"Ellen",
         "lastName":"Schwarm",
         "priceRange":"1",
         "pets":"0",
         "smoking":"1",
         "pool":"1",
         "gym":"1",
         "parking":"0",
         "laundry":"0",
         "numRoomates":"3",
         "distanceToWork":"2",
         "roommateGender":"1",
         "typeOfResidence":"1"
      },
      {
         "firstName":"Amy",
         "lastName":"Weaton",
         "priceRange":"1",
         "pets":"1",
         "smoking":"1",
         "pool":"0",
         "gym":"1",
         "parking":"1",
         "laundry":"1",
         "numRoomates":"1",
         "distanceToWork":"1",
         "roommateGender":"0",
         "typeOfResidence":"1"
      },
      {
         "firstName":"Taylor",
         "lastName":"Wong",
         "priceRange":"1",
         "pets":"1",
         "smoking":"1",
         "pool":"0",
         "gym":"0",
         "parking":"1",
         "laundry":"1",
         "numRoomates":"2",
         "distanceToWork":"2",
         "roommateGender":"0",
         "typeOfResidence":"2"
      }
   ]
}